{
  "function": "minecraft:sequence",
  "functions": [
    {
      "function": "minecraft:set_custom_data",
      "tag": {
        "morecombat": {
          "state": "morecombat:snout"
        }
      }
    },
    {
      "function": "minecraft:set_custom_model_data",
      "strings": {
        "values": [
          "snout"
        ],
        "mode": "replace_all"
      }
    },
    {
      "function": "minecraft:set_components",
      "components": {
        "minecraft:item_name": {
          "translate": "item.morecombat.wand.snout",
          "fallback": "Snout Rod",
          "bold": false,
          "italic": false,
          "underlined": false,
          "strikethrough": false,
          "obfuscated": false
        }
      }
    },
    {
      "function": "minecraft:set_lore",
      "mode": "replace_all",
      "lore": [
        {
          "translate": "item.morecombat.wand.snout.description",
          "fallback": "Shoots 3 Blaze Fireballs",
          "color": "gray",
          "bold": false,
          "italic": true,
          "underlined": false,
          "strikethrough": false,
          "obfuscated": false
        },
        {
          "translate": "item.morecombat.wand.snout.description",
          "fallback": "If sneaking, shoots a Ghast Fireball",
          "color": "gray",
          "bold": false,
          "italic": true,
          "underlined": false,
          "strikethrough": false,
          "obfuscated": false
        }
      ]
    }
  ]
}